.gitignore
LICENSE.txt
MANIFEST.in
README.md
ncdirect-pydemo
ncdirect-pydemo.1.md
notcurses-pydemo
notcurses-pydemo.1.md
setup.cfg
setup.py
include/notcurses/direct.h
include/notcurses/nckeys.h
include/notcurses/ncport.h
include/notcurses/ncseqs.h
include/notcurses/notcurses.h
src/notcurses/__init__.py
src/notcurses/build_notcurses.py
src/notcurses/notcurses.py
src/notcurses.egg-info/PKG-INFO
src/notcurses.egg-info/SOURCES.txt
src/notcurses.egg-info/dependency_links.txt
src/notcurses.egg-info/requires.txt
src/notcurses.egg-info/top_level.txt
src/notcurses.egg-info/zip-safe