Metadata-Version: 2.4
Name: notcurses
Version: 3.0.16
Summary: Blingful TUI construction library (python bindings)
Home-page: https://github.com/dankamongmen/notcurses
Author: Nick Black
Author-email: nickblack@linux.com
License: Apache License, Version 2.0
Keywords: ncurses curses tui console graphics
Platform: any
Classifier: Development Status :: 4 - Beta
Classifier: Environment :: Console
Classifier: License :: OSI Approved :: Apache Software License
Classifier: Natural Language :: English
Classifier: Programming Language :: Python
License-File: LICENSE.txt
Requires-Dist: cffi>=1.0.0
Dynamic: author
Dynamic: author-email
Dynamic: classifier
Dynamic: description
Dynamic: description-content-type
Dynamic: home-page
Dynamic: keywords
Dynamic: license
Dynamic: license-file
Dynamic: platform
Dynamic: requires-dist
Dynamic: summary
